{
  "第01課": [
    "簽",
    "遞",
    "傻",
    "瓜",
    "若",
    "續",
    "痺",
    "患",
    "握",
    "博",
    "聆",
    "肢",
    "埋",
    "擔",
    "談",
    "懸",
    "章",
    "符"
  ],
  "第02課": [
    "匹",
    "怒",
    "廷",
    "妥",
    "諫",
    "閉",
    "覷",
    "犯",
    "罪",
    "仁",
    "政",
    "斥",
    "蒙",
    "羞",
    "懂",
    "委",
    "婉",
    "勸"
  ],
  "第03課": [
    "輛",
    "屢",
    "姍",
    "抵",
    "返",
    "率",
    "鄰",
    "領",
    "梭",
    "隼",
    "較",
    "贏",
    "逐",
    "旦",
    "遭",
    "評",
    "普",
    "承",
    "搏"
  ],
  "第04課": [
    "診",
    "繃",
    "緒",
    "疫",
    "篩",
    "偉",
    "雄",
    "補",
    "驟",
    "菊",
    "罩",
    "塵",
    "槌",
    "餘",
    "撥",
    "廓",
    "拼",
    "湊",
    "骨"
  ],
  "第05課": [
    "盈",
    "浸",
    "稀",
    "儲",
    "寵",
    "寂",
    "螢",
    "仿",
    "彿",
    "悉",
    "賦",
    "詞",
    "龍",
    "冠",
    "鳳",
    "紋",
    "飾",
    "閱",
    "湧"
  ],
  "第06課": [
    "賭",
    "杯",
    "奏",
    "魔",
    "脆",
    "嗓",
    "啞",
    "咳",
    "促",
    "喘",
    "吁",
    "伏",
    "唷",
    "須",
    "憂",
    "增",
    "詮",
    "魅"
  ],
  "第07課": [
    "證",
    "檢",
    "鯨",
    "殖",
    "哺",
    "乳",
    "胎",
    "漲",
    "汐",
    "週",
    "撈",
    "滬",
    "省",
    "施",
    "哲",
    "圈",
    "柢"
  ],
  "第08課": [
    "涵",
    "珊",
    "瑚",
    "鯊",
    "豚",
    "抹",
    "噴",
    "譟",
    "鏽",
    "錨",
    "牧",
    "窺",
    "筒",
    "琉",
    "璃",
    "凸",
    "襯",
    "托",
    "玻"
  ],
  "第09課": [
    "積",
    "噸",
    "垃",
    "圾",
    "謎",
    "貨",
    "循",
    "菌",
    "鉤",
    "鏈",
    "孔",
    "倖",
    "據",
    "宜",
    "估",
    "廢",
    "踐",
    "益",
    "殼"
  ],
  "第10課": [
    "蹟",
    "蕩",
    "洪",
    "誕",
    "沼",
    "澤",
    "豹",
    "效",
    "栩",
    "跺",
    "蘆",
    "葦",
    "堪",
    "洶",
    "鵡",
    "狼",
    "絕",
    "挑",
    "剔"
  ],
  "第11課": [
    "婪",
    "嚎",
    "群",
    "疼",
    "魂",
    "規",
    "違",
    "駕",
    "橫",
    "屑",
    "瀑",
    "瀉",
    "燃",
    "噬",
    "延",
    "籠",
    "焰",
    "霆",
    "啄"
  ],
  "第12課": [
    "穀",
    "亡",
    "授",
    "臟",
    "誤",
    "眩",
    "燥",
    "咀",
    "症",
    "嗚",
    "犧",
    "牲",
    "赭",
    "鞭",
    "藤",
    "蔓",
    "摘",
    "責",
    "佑"
  ]
}